knwkrma_api/__init__.py
knwkrma_api/_main.py
knwkrma_api-1.0.3.dist-info/LICENSE
knwkrma_api-1.0.3.dist-info/METADATA
knwkrma_api-1.0.3.dist-info/WHEEL
knwkrma_api-1.0.3.dist-info/RECORD
